events_scraper/__init__.py
events_scraper/events_scraper.py
events_scraper-0.1.0.dist-info/LICENSE
events_scraper-0.1.0.dist-info/METADATA
events_scraper-0.1.0.dist-info/WHEEL
events_scraper-0.1.0.dist-info/top_level.txt
events_scraper-0.1.0.dist-info/RECORD
