Metadata-Version: 2.1
Name: events-scraper
Version: 0.1.0
Summary: A Python package to fetch events using Ticketmaster API
Home-page: https://github.com/sulynajimsj/events-scraper
Author: Suleiman Najim
Author-email: Sulysalim@hotmail.com
Classifier: Programming Language :: Python :: 3
Classifier: License :: OSI Approved :: MIT License
Classifier: Operating System :: OS Independent
Requires-Python: >=3.6
License-File: LICENSE
Requires-Dist: requests
